kineticauth/__init__.py
kineticauth/keys.py
kineticauth-0.0.1.dist-info/METADATA
kineticauth-0.0.1.dist-info/WHEEL
kineticauth-0.0.1.dist-info/top_level.txt
kineticauth-0.0.1.dist-info/RECORD
